chill/__init__.py
chill/_version.py
chill/api.py
chill/app.py
chill/database.py
chill/migrations.py
chill/public.py
chill/script.py
chill/shortcodes.py
chill/test_api.py
chill/test_loader.py
chill/tests.py
chill/yaml_chill_node.py
chill/queries/create_chill.sql
chill/queries/create_image.sql
chill/queries/create_node.sql
chill/queries/create_node_node.sql
chill/queries/create_node_picture.sql
chill/queries/create_picture.sql
chill/queries/create_query.sql
chill/queries/create_route.sql
chill/queries/create_srcset.sql
chill/queries/create_staticfile.sql
chill/queries/create_template.sql
chill/queries/delete_node_for_id.sql
chill/queries/drop_chill.sql
chill/queries/drop_node.sql
chill/queries/drop_node_node.sql
chill/queries/drop_query.sql
chill/queries/drop_route.sql
chill/queries/drop_template.sql
chill/queries/insert_image.sql
chill/queries/insert_node.sql
chill/queries/insert_node_node.sql
chill/queries/insert_node_picture.sql
chill/queries/insert_picture.sql
chill/queries/insert_query.sql
chill/queries/insert_query_node.sql
chill/queries/insert_route.sql
chill/queries/insert_staticfile.sql
chill/queries/insert_template.sql
chill/queries/select_all_chill_nodes.sql
chill/queries/select_all_nodes.sql
chill/queries/select_link_node_from_node.sql
chill/queries/select_node_from_id.sql
chill/queries/select_node_from_name.sql
chill/queries/select_node_from_route.sql
chill/queries/select_node_node_from_node_id.sql
chill/queries/select_paths_to_freeze.sql
chill/queries/select_picture_by_name.sql
chill/queries/select_picture_for_node.sql
chill/queries/select_query_from_node.sql
chill/queries/select_query_where_name.sql
chill/queries/select_route_where_dynamic.sql
chill/queries/select_staticfile.sql
chill/queries/select_template.sql
chill/queries/select_template_from_node.sql
chill/queries/set_current_chill_version.sql
chill/queries/update_node_for_id.sql
chill/queries/update_template_node.sql
chill-0.10.1.dist-info/METADATA
chill-0.10.1.dist-info/WHEEL
chill-0.10.1.dist-info/entry_points.txt
chill-0.10.1.dist-info/licenses/COPYING
chill-0.10.1.dist-info/licenses/COPYING.LESSER
chill-0.10.1.dist-info/RECORD
