Metadata-Version: 2.3
Name: chill
Version: 0.10.1
Summary: Database driven web application framework in Flask
Project-URL: Homepage, https://git.sr.ht/~jkenlooper/chill
Author-email: Jake Hickenlooper <jake@massive.xyz>
License: LGPLv3+
Classifier: Development Status :: 4 - Beta
Classifier: Environment :: Console
Classifier: Environment :: Web Environment
Classifier: Framework :: Flask
Classifier: Intended Audience :: Developers
Classifier: Intended Audience :: Information Technology
Classifier: License :: OSI Approved :: GNU Lesser General Public License v3 or later (LGPLv3+)
Classifier: Natural Language :: English
Classifier: Operating System :: POSIX
Classifier: Programming Language :: Python :: 3.10
Classifier: Programming Language :: Python :: 3.11
Classifier: Topic :: Internet :: WWW/HTTP :: Site Management
Classifier: Topic :: Internet :: WWW/HTTP :: WSGI
Classifier: Topic :: Software Development :: Build Tools
Requires-Python: <4,>=3.10
Requires-Dist: babel
Requires-Dist: flask-caching
Requires-Dist: flask>=3
Requires-Dist: humanize
Requires-Dist: markdown
Requires-Dist: markupsafe
Requires-Dist: pyyaml
Provides-Extra: cli
Requires-Dist: docopt>=0.6.2; extra == 'cli'
Requires-Dist: frozen-flask>=1; extra == 'cli'
Requires-Dist: gunicorn>=21; extra == 'cli'
Provides-Extra: dev
Provides-Extra: test
Requires-Dist: coverage; extra == 'test'
Requires-Dist: pytest; extra == 'test'
